symmetric_synthetic/__init__.py
symmetric_synthetic/data_process.py
symmetric_synthetic/shape_generate.py
symmetric_synthetic-0.1.0.dist-info/entry_points.txt
symmetric_synthetic-0.1.0.dist-info/LICENSE
symmetric_synthetic-0.1.0.dist-info/WHEEL
symmetric_synthetic-0.1.0.dist-info/METADATA
symmetric_synthetic-0.1.0.dist-info/RECORD
