Metadata-Version: 2.1
Name: symmetric-synthetic
Version: 0.1.0
Summary: create symmetrical objects in synthetic images and their corresponding mask
Home-page: https://github.com/danushv07/symmetric_synthetic
License: BSD-3-Clause
Author: Danush Kumar Venkatesh
Requires-Python: >=3.8,<4.0
Classifier: License :: OSI Approved :: BSD License
Classifier: Programming Language :: Python :: 3
Classifier: Programming Language :: Python :: 3.10
Classifier: Programming Language :: Python :: 3.8
Classifier: Programming Language :: Python :: 3.9
Requires-Dist: click
Requires-Dist: numpy (>=1.21.0,<2.0.0)
Requires-Dist: pillow (>=9.1.0,<10.0.0)
Requires-Dist: scikit-image (>=0.17.2,<0.18.0)
Requires-Dist: scipy (>=1.4.1,<2.0.0)
Project-URL: Repository, https://github.com/danushv07/symmetric_synthetic
